swain_cli/__init__.py
swain_cli/__main__.py
swain_cli/args.py
swain_cli/auth.py
swain_cli/cli.py
swain_cli/console.py
swain_cli/constants.py
swain_cli/crudsql.py
swain_cli/engine.py
swain_cli/errors.py
swain_cli/generator.py
swain_cli/http.py
swain_cli/interactive.py
swain_cli/openapi_spec.py
swain_cli/prompts.py
swain_cli/swain_api.py
swain_cli/urls.py
swain_cli/utils.py
swain_cli/version.py
swain_cli-0.3.13.dist-info/licenses/LICENSE
swain_cli-0.3.13.dist-info/METADATA
swain_cli-0.3.13.dist-info/WHEEL
swain_cli-0.3.13.dist-info/entry_points.txt
swain_cli-0.3.13.dist-info/top_level.txt
swain_cli-0.3.13.dist-info/RECORD
