Metadata-Version: 2.4
Name: swain_cli
Version: 0.3.13
Summary: Zero-setup SDK generator wrapping OpenAPI Generator
Author: Swain Labs
License-Expression: Apache-2.0
Project-URL: Homepage, https://github.com/takifouhal/swain_cli
Project-URL: Repository, https://github.com/takifouhal/swain_cli
Keywords: openapi,swagger,sdk,codegen,cli
Classifier: Development Status :: 3 - Alpha
Classifier: Intended Audience :: Developers
Classifier: Programming Language :: Python
Classifier: Programming Language :: Python :: 3
Classifier: Programming Language :: Python :: 3 :: Only
Classifier: Programming Language :: Python :: 3.8
Classifier: Programming Language :: Python :: 3.9
Classifier: Programming Language :: Python :: 3.10
Classifier: Programming Language :: Python :: 3.11
Classifier: Programming Language :: Python :: 3.12
Requires-Python: >=3.8
License-File: LICENSE
Requires-Dist: platformdirs>=3.11
Requires-Dist: httpx>=0.26
Requires-Dist: pooch>=1.8
Requires-Dist: typer>=0.12
Requires-Dist: questionary>=2.0
Requires-Dist: keyring>=24
Provides-Extra: dev
Requires-Dist: pytest>=7; extra == "dev"
Provides-Extra: lint
Requires-Dist: ruff>=0.6; python_version >= "3.9" and extra == "lint"
Requires-Dist: mypy>=1.8; python_version >= "3.9" and extra == "lint"
Dynamic: license-file
